rinoh_typeface_texgyreheros/GUST-FONT-LICENSE.txt
rinoh_typeface_texgyreheros/README-TeX-Gyre-Heros.txt
rinoh_typeface_texgyreheros/__init__.py
rinoh_typeface_texgyreheros/texgyreheros-bold.otf
rinoh_typeface_texgyreheros/texgyreheros-bolditalic.otf
rinoh_typeface_texgyreheros/texgyreheros-italic.otf
rinoh_typeface_texgyreheros/texgyreheros-regular.otf
rinoh_typeface_texgyreheros/texgyreheroscn-bold.otf
rinoh_typeface_texgyreheros/texgyreheroscn-bolditalic.otf
rinoh_typeface_texgyreheros/texgyreheroscn-italic.otf
rinoh_typeface_texgyreheros/texgyreheroscn-regular.otf
rinoh_typeface_texgyreheros-0.1.1.dist-info/DESCRIPTION.rst
rinoh_typeface_texgyreheros-0.1.1.dist-info/METADATA
rinoh_typeface_texgyreheros-0.1.1.dist-info/RECORD
rinoh_typeface_texgyreheros-0.1.1.dist-info/WHEEL
rinoh_typeface_texgyreheros-0.1.1.dist-info/entry_points.txt
rinoh_typeface_texgyreheros-0.1.1.dist-info/metadata.json
rinoh_typeface_texgyreheros-0.1.1.dist-info/top_level.txt
