Metadata-Version: 1.1
Name: rinoh-typeface-texgyreheros
Version: 0.1.1
Summary: TeX Gyre Heros typeface
Home-page: https://github.com/brechtm/rinoh-typeface-texgyreheros
Author: Brecht Machiels
Author-email: brecht@mos6581.org
License: GUST Font License (GFL)
Keywords: opentype font
Platform: UNKNOWN
Classifier: Intended Audience :: Developers
Classifier: Intended Audience :: End Users/Desktop
Classifier: Operating System :: OS Independent
Classifier: Programming Language :: Python
Classifier: Programming Language :: Python :: 3
Classifier: Topic :: Text Processing :: Fonts
